// class version 50.0 (50)
// access flags 0x21
public class Packet {

  // compiled from: Test.scala

  @Lscala/reflect/ScalaSignature;(bytes="\u0006\u0001\u00193A!\u0001\u0002\u0001\u000b\u00091\u0001+Y2lKRT\u0011aA\u0001\u0008y\u0015l\u0007\u000f^=?\u0007\u0001\u0019\"\u0001\u0001\u0004\u0011\u0005\u001dQQ\"\u0001\u0005\u000b\u0003%\u0009Qa]2bY\u0006L!a\u0003\u0005\u0003\r\u0005s\u0017PU3g\u0011!i\u0001A!a\u0001\n\u0003q\u0011\u0001\u00027j].,\u0012a\u0004\u0009\u0003!\u0001i\u0011A\u0001\u0005\u0009%\u0001\u0011\u0009\u0019!C\u0001'\u0005AA.\u001b8l?\u0012*\u0017\u000f\u0006\u0002\u0015/A\u0011q!F\u0005\u0003-!\u0011A!\u00168ji\"9\u0001$EA\u0001\u0002\u0004y\u0011a\u0001=%c!A!\u0004\u0001B\u0001B\u0003&q\"A\u0003mS:\\\u0007\u0005\u0003\u0005\u001d\u0001\u0009\u0005\r\u0011\"\u0001\u001e\u0003\u0009IG-F\u0001\u001f!\u00099q$\u0003\u0002!\u0011\u0009\u0019\u0011J\u001c;\u0009\u0011\u0009\u0002!\u00111A\u0005\u0002\r\na!\u001b3`I\u0015\u000cHC\u0001\u000b%\u0011\u001dA\u0012%!AA\u0002yA\u0001B\n\u0001\u0003\u0002\u0003\u0006KAH\u0001\u0004S\u0012\u0004\u0003\u0002\u0003\u0015\u0001\u0005\u000b\u0007I\u0011A\u000f\u0002\u0009-Lg\u000e\u001a\u0005\u0009U\u0001\u0011\u0009\u0011)A\u0005=\u0005)1.\u001b8eA!)A\u0006\u0001C\u0001[\u00051A(\u001b8jiz\"Ba\u0004\u00180a!)Qb\u000ba\u0001\u001f!)Ad\u000ba\u0001=!)\u0001f\u000ba\u0001=!9!\u0007\u0001a\u0001\n\u0003i\u0012AA12\u0011\u001d!\u0004\u00011A\u0005\u0002U\na!Y\u0019`I\u0015\u000cHC\u0001\u000b7\u0011\u001dA2'!AA\u0002yAa\u0001\u000f\u0001!B\u0013q\u0012aA12A!9!\u0008\u0001b\u0001\n\u0003Y\u0014AA13+\u0005a\u0004cA\u0004>=%\u0011a\u0008\u0003\u0002\u0006\u0003J\u0014\u0018-\u001f\u0005\u0007\u0001\u0002\u0001\u000b\u0011\u0002\u001f\u0002\u0007\u0005\u0014\u0004\u0005C\u0003C\u0001\u0011\u00051)A\u0003bI\u0012$v\u000e\u0006\u0002\u0010\u0009\")Q)\u0011a\u0001\u001f\u0005)\u0011/^3vK\u0002")

  ATTRIBUTE ScalaSig : unknown

  ATTRIBUTE ScalaInlineInfo : unknown

  // access flags 0x2
  private LPacket; link

  // access flags 0x2
  private I id

  // access flags 0x12
  private final I kind

  // access flags 0x2
  private I a1

  // access flags 0x12
  private final [I a2

  // access flags 0x1
  public link()LPacket;
   L0
    LINENUMBER 403 L0
    ALOAD 0
    GETFIELD Packet.link : LPacket;
    ARETURN
   L1
    LOCALVARIABLE this LPacket; L0 L1 0
    MAXSTACK = 1
    MAXLOCALS = 1

  // access flags 0x1
  public link_$eq(LPacket;)V
   L0
    LINENUMBER 403 L0
    ALOAD 0
    ALOAD 1
    PUTFIELD Packet.link : LPacket;
    RETURN
   L1
    LOCALVARIABLE this LPacket; L0 L1 0
    LOCALVARIABLE x$1 LPacket; L0 L1 1
    MAXSTACK = 2
    MAXLOCALS = 2

  // access flags 0x1
  public id()I
   L0
    LINENUMBER 403 L0
    ALOAD 0
    GETFIELD Packet.id : I
    IRETURN
   L1
    LOCALVARIABLE this LPacket; L0 L1 0
    MAXSTACK = 1
    MAXLOCALS = 1

  // access flags 0x1
  public id_$eq(I)V
   L0
    LINENUMBER 403 L0
    ALOAD 0
    ILOAD 1
    PUTFIELD Packet.id : I
    RETURN
   L1
    LOCALVARIABLE this LPacket; L0 L1 0
    LOCALVARIABLE x$1 I L0 L1 1
    MAXSTACK = 2
    MAXLOCALS = 2

  // access flags 0x1
  public kind()I
   L0
    LINENUMBER 403 L0
    ALOAD 0
    GETFIELD Packet.kind : I
    IRETURN
   L1
    LOCALVARIABLE this LPacket; L0 L1 0
    MAXSTACK = 1
    MAXLOCALS = 1

  // access flags 0x1
  public a1()I
   L0
    LINENUMBER 405 L0
    ALOAD 0
    GETFIELD Packet.a1 : I
    IRETURN
   L1
    LOCALVARIABLE this LPacket; L0 L1 0
    MAXSTACK = 1
    MAXLOCALS = 1

  // access flags 0x1
  public a1_$eq(I)V
   L0
    LINENUMBER 405 L0
    ALOAD 0
    ILOAD 1
    PUTFIELD Packet.a1 : I
    RETURN
   L1
    LOCALVARIABLE this LPacket; L0 L1 0
    LOCALVARIABLE x$1 I L0 L1 1
    MAXSTACK = 2
    MAXLOCALS = 2

  // access flags 0x1
  public a2()[I
   L0
    LINENUMBER 406 L0
    ALOAD 0
    GETFIELD Packet.a2 : [I
    ARETURN
   L1
    LOCALVARIABLE this LPacket; L0 L1 0
    MAXSTACK = 1
    MAXLOCALS = 1

  // access flags 0x1
  public addTo(LPacket;)LPacket;
   L0
    LINENUMBER 410 L0
    ALOAD 0
    ACONST_NULL
    POP
    ACONST_NULL
    INVOKEVIRTUAL Packet.link_$eq (LPacket;)V
   L1
    LINENUMBER 411 L1
    ALOAD 1
    IFNULL L2
    GOTO L3
   L2
    LINENUMBER 412 L2
   FRAME SAME
    ALOAD 0
    GOTO L4
   L3
    LINENUMBER 414 L3
   FRAME SAME
    ALOAD 1
   L5
    ASTORE 2
   L6
    LINENUMBER 415 L6
   FRAME APPEND [Packet]
    ALOAD 2
    INVOKEVIRTUAL Packet.link ()LPacket;
    IFNULL L7
    GOTO L8
   L8
    LINENUMBER 416 L8
   FRAME SAME
    ALOAD 2
    INVOKEVIRTUAL Packet.link ()LPacket;
    ASTORE 2
    GOTO L6
   L7
    LINENUMBER 417 L7
   FRAME SAME
    ALOAD 2
    ALOAD 0
    INVOKEVIRTUAL Packet.link_$eq (LPacket;)V
   L9
    LINENUMBER 418 L9
    ALOAD 1
   L4
   FRAME FULL [Packet Packet] [Packet]
    ARETURN
   L10
    LOCALVARIABLE next LPacket; L5 L4 2
    LOCALVARIABLE this LPacket; L0 L10 0
    LOCALVARIABLE queue LPacket; L0 L10 1
    MAXSTACK = 2
    MAXLOCALS = 3

  // access flags 0x1
  public <init>(LPacket;II)V
   L0
    LINENUMBER 403 L0
    ALOAD 0
    ALOAD 1
    PUTFIELD Packet.link : LPacket;
    ALOAD 0
    ILOAD 2
    PUTFIELD Packet.id : I
    ALOAD 0
    ILOAD 3
    PUTFIELD Packet.kind : I
   L1
    LINENUMBER 422 L1
    ALOAD 0
    INVOKESPECIAL java/lang/Object.<init> ()V
   L2
    LINENUMBER 405 L2
    ALOAD 0
    ICONST_0
    PUTFIELD Packet.a1 : I
   L3
    LINENUMBER 406 L3
    ALOAD 0
    ICONST_4
    NEWARRAY T_INT
    PUTFIELD Packet.a2 : [I
   L4
    LINENUMBER 403 L4
    RETURN
   L5
    LOCALVARIABLE this LPacket; L0 L5 0
    LOCALVARIABLE link LPacket; L0 L5 1
    LOCALVARIABLE id I L0 L5 2
    LOCALVARIABLE kind I L0 L5 3
    MAXSTACK = 2
    MAXLOCALS = 4
}
