// class version 50.0 (50)
// access flags 0x21
public class Richards {

  // compiled from: Test.scala

  @Lscala/reflect/ScalaSignature;(bytes="\u0006\u0001A4A!\u0001\u0002\u0001\u000b\u0009A!+[2iCJ$7OC\u0001\u0004\u0003\u001daT-\u001c9usz\u001a\u0001a\u0005\u0002\u0001\rA\u0011qAC\u0007\u0002\u0011)\u0009\u0011\"A\u0003tG\u0006d\u0017-\u0003\u0002\u000c\u0011\u00091\u0011I\\=SK\u001aDQ!\u0004\u0001\u0005\u00029\u0009a\u0001P5oSRtD#A\u0008\u0011\u0005A\u0001Q\"\u0001\u0002\u0009\u000bI\u0001A\u0011A\n\u0002\u0007I,h\u000eF\u0001\u0015!\u00099Q#\u0003\u0002\u0017\u0011\u0009!QK\\5u\u000f\u0015A\"\u0001#\u0001\u001a\u0003!\u0011\u0016n\u00195be\u0012\u001c\u0008C\u0001\u0009\u001b\r\u0015\u0009!\u0001#\u0001\u001c'\u0009Qb\u0001C\u0003\u000e5\u0011\u0005Q\u0004F\u0001\u001a\u0011\u001dy\"D1A\u0005\u0006\u0001\n\u0011\u0002R!U\u0003~\u001b\u0016JW#\u0016\u0003\u0005z\u0011AI\u000f\u0002\u0009!1AE\u0007Q\u0001\u000e\u0005\n!\u0002R!U\u0003~\u001b\u0016JW#!\u0011\u001d1#D1A\u0005\u0006\u001d\nQaQ(V\u001dR+\u0012\u0001K\u0008\u0002Su\u00111\u0001;\u0005\u0007Wi\u0001\u000bQ\u0002\u0015\u0002\r\r{UK\u0014+!\u0011\u001di#D1A\u0005\u00069\nA#\u0012-Q\u000b\u000e#V\u0009R0R+\u0016+ViX\"P+:#V#A\u0018\u0010\u0003Aj\"!\u0003\n\u0009\rIR\u0002\u0015!\u00040\u0003U)\u0005\u000cU#D)\u0016#u,U+F+\u0016{6iT+O)\u0002Bq\u0001\u000e\u000eC\u0002\u0013\u0015Q'A\nF1B+5\u0009V#E?\"{E\nR0D\u001fVsE+F\u00017\u001f\u00059TDA\u0002!\u0012\u0019I$\u0004)A\u0007m\u0005!R\u0009\u0017)F\u0007R+Ei\u0018%P\u0019\u0012{6iT+O)\u0002Bqa\u000f\u000eC\u0002\u0013\u0015A(A\u0004J\u0009~KE\u0009T#\u0016\u0003uz\u0011AP\u000f\u0002\u0001!1\u0001I\u0007Q\u0001\u000eu\n\u0001\"\u0013#`\u0013\u0012cU\u0009\u0009\u0005\u0008\u0005j\u0011\r\u0011\"\u0002D\u0003%IEiX,P%.+%+F\u0001E\u001f\u0005)U$A\u0001\u0009\r\u001dS\u0002\u0015!\u0004E\u0003)IEiX,P%.+%\u000b\u0009\u0005\u0008\u0013j\u0011\r\u0011\"\u0002K\u00031IEi\u0018%B\u001d\u0012cUIU0B+\u0005Yu\"\u0001'\u001e\u0003\u0009AaA\u0014\u000e!\u0002\u001bY\u0015!D%E?\"\u000be\n\u0012'F%~\u000b\u0005\u0005C\u0004Q5\u0009\u0007IQA)\u0002\u0019%#u\u000cS!O\u00092+%k\u0018\"\u0016\u0003I{\u0011aU\u000f\u0002\u0007!1QK\u0007Q\u0001\u000eI\u000bQ\"\u0013#`\u0011\u0006sE\u0009T#S?\n\u0003\u0003bB,\u001b\u0005\u0004%)\u0001I\u0001\u000c\u0013\u0012{F)\u0012,J\u0007\u0016{\u0016\u0009\u0003\u0004Z5\u0001\u0006i!I\u0001\r\u0013\u0012{F)\u0012,J\u0007\u0016{\u0016\u0009\u0009\u0005\u00087j\u0011\r\u0011\"\u0002]\u0003-IEi\u0018#F-&\u001bUi\u0018\"\u0016\u0003u{\u0011AX\u000f\u0002\u000b!1\u0001M\u0007Q\u0001\u000eu\u000bA\"\u0013#`\u0009\u00163\u0016jQ#`\u0005\u0002BqA\u0019\u000eC\u0002\u0013\u00151-A\u0007O+6\u0013UIU0P\r~KEiU\u000b\u0002I>\u0009Q-H\u0001\u0007\u0011\u00199'\u0004)A\u0007I\u0006qa*V'C\u000bJ{vJR0J\u0009N\u0003\u0003bB5\u001b\u0005\u0004%)\u0001P\u0001\u000c\u0017&sEi\u0018#F-&\u001bU\u0009\u0003\u0004l5\u0001\u0006i!P\u0001\r\u0017&sEi\u0018#F-&\u001bU\u0009\u0009\u0005\u0008[j\u0011\r\u0011\"\u0002D\u0003%Y\u0015J\u0014#`/>\u00136\n\u0003\u0004p5\u0001\u0006i\u0001R\u0001\u000b\u0017&sEiX,P%.\u0003\u0003")

  ATTRIBUTE ScalaSig : unknown

  ATTRIBUTE ScalaInlineInfo : unknown

  // access flags 0x9
  public static KIND_WORK()I
    GETSTATIC Richards$.MODULE$ : LRichards$;
    INVOKEVIRTUAL Richards$.KIND_WORK ()I
    IRETURN
    MAXSTACK = 1
    MAXLOCALS = 0

  // access flags 0x9
  public static KIND_DEVICE()I
    GETSTATIC Richards$.MODULE$ : LRichards$;
    INVOKEVIRTUAL Richards$.KIND_DEVICE ()I
    IRETURN
    MAXSTACK = 1
    MAXLOCALS = 0

  // access flags 0x9
  public static NUMBER_OF_IDS()I
    GETSTATIC Richards$.MODULE$ : LRichards$;
    INVOKEVIRTUAL Richards$.NUMBER_OF_IDS ()I
    IRETURN
    MAXSTACK = 1
    MAXLOCALS = 0

  // access flags 0x9
  public static ID_DEVICE_B()I
    GETSTATIC Richards$.MODULE$ : LRichards$;
    INVOKEVIRTUAL Richards$.ID_DEVICE_B ()I
    IRETURN
    MAXSTACK = 1
    MAXLOCALS = 0

  // access flags 0x9
  public static ID_DEVICE_A()I
    GETSTATIC Richards$.MODULE$ : LRichards$;
    INVOKEVIRTUAL Richards$.ID_DEVICE_A ()I
    IRETURN
    MAXSTACK = 1
    MAXLOCALS = 0

  // access flags 0x9
  public static ID_HANDLER_B()I
    GETSTATIC Richards$.MODULE$ : LRichards$;
    INVOKEVIRTUAL Richards$.ID_HANDLER_B ()I
    IRETURN
    MAXSTACK = 1
    MAXLOCALS = 0

  // access flags 0x9
  public static ID_HANDLER_A()I
    GETSTATIC Richards$.MODULE$ : LRichards$;
    INVOKEVIRTUAL Richards$.ID_HANDLER_A ()I
    IRETURN
    MAXSTACK = 1
    MAXLOCALS = 0

  // access flags 0x9
  public static ID_WORKER()I
    GETSTATIC Richards$.MODULE$ : LRichards$;
    INVOKEVIRTUAL Richards$.ID_WORKER ()I
    IRETURN
    MAXSTACK = 1
    MAXLOCALS = 0

  // access flags 0x9
  public static ID_IDLE()I
    GETSTATIC Richards$.MODULE$ : LRichards$;
    INVOKEVIRTUAL Richards$.ID_IDLE ()I
    IRETURN
    MAXSTACK = 1
    MAXLOCALS = 0

  // access flags 0x9
  public static EXPECTED_HOLD_COUNT()I
    GETSTATIC Richards$.MODULE$ : LRichards$;
    INVOKEVIRTUAL Richards$.EXPECTED_HOLD_COUNT ()I
    IRETURN
    MAXSTACK = 1
    MAXLOCALS = 0

  // access flags 0x9
  public static EXPECTED_QUEUE_COUNT()I
    GETSTATIC Richards$.MODULE$ : LRichards$;
    INVOKEVIRTUAL Richards$.EXPECTED_QUEUE_COUNT ()I
    IRETURN
    MAXSTACK = 1
    MAXLOCALS = 0

  // access flags 0x9
  public static COUNT()I
    GETSTATIC Richards$.MODULE$ : LRichards$;
    INVOKEVIRTUAL Richards$.COUNT ()I
    IRETURN
    MAXSTACK = 1
    MAXLOCALS = 0

  // access flags 0x9
  public static DATA_SIZE()I
    GETSTATIC Richards$.MODULE$ : LRichards$;
    INVOKEVIRTUAL Richards$.DATA_SIZE ()I
    IRETURN
    MAXSTACK = 1
    MAXLOCALS = 0

  // access flags 0x1
  public run()V
   L0
    LINENUMBER 5 L0
    NEW Scheduler
    DUP
    INVOKESPECIAL Scheduler.<init> ()V
   L1
    ASTORE 1
   L2
    LINENUMBER 6 L2
    ALOAD 1
    ICONST_0
    ICONST_0
    ACONST_NULL
    POP
    ACONST_NULL
    SIPUSH 1000
    INVOKEVIRTUAL Scheduler.addIdleTask (IILPacket;I)V
   L3
    LINENUMBER 8 L3
    NEW Packet
    DUP
    ACONST_NULL
    POP
    ACONST_NULL
    ICONST_1
    ICONST_1
    INVOKESPECIAL Packet.<init> (LPacket;II)V
   L4
    ASTORE 2
   L5
    LINENUMBER 9 L5
    NEW Packet
    DUP
    ALOAD 2
    ICONST_1
    ICONST_1
    INVOKESPECIAL Packet.<init> (LPacket;II)V
    ASTORE 2
   L6
    LINENUMBER 10 L6
    ALOAD 1
    ICONST_1
    SIPUSH 1000
    ALOAD 2
    INVOKEVIRTUAL Scheduler.addWorkerTask (IILPacket;)V
   L7
    LINENUMBER 12 L7
    NEW Packet
    DUP
    ACONST_NULL
    POP
    ACONST_NULL
    ICONST_4
    ICONST_0
    INVOKESPECIAL Packet.<init> (LPacket;II)V
    ASTORE 2
   L8
    LINENUMBER 13 L8
    NEW Packet
    DUP
    ALOAD 2
    ICONST_4
    ICONST_0
    INVOKESPECIAL Packet.<init> (LPacket;II)V
    ASTORE 2
   L9
    LINENUMBER 14 L9
    NEW Packet
    DUP
    ALOAD 2
    ICONST_4
    ICONST_0
    INVOKESPECIAL Packet.<init> (LPacket;II)V
    ASTORE 2
   L10
    LINENUMBER 15 L10
    ALOAD 1
    ICONST_2
    SIPUSH 2000
    ALOAD 2
    INVOKEVIRTUAL Scheduler.addHandlerTask (IILPacket;)V
   L11
    LINENUMBER 17 L11
    NEW Packet
    DUP
    ACONST_NULL
    POP
    ACONST_NULL
    ICONST_5
    ICONST_0
    INVOKESPECIAL Packet.<init> (LPacket;II)V
    ASTORE 2
   L12
    LINENUMBER 18 L12
    NEW Packet
    DUP
    ALOAD 2
    ICONST_5
    ICONST_0
    INVOKESPECIAL Packet.<init> (LPacket;II)V
    ASTORE 2
   L13
    LINENUMBER 19 L13
    NEW Packet
    DUP
    ALOAD 2
    ICONST_5
    ICONST_0
    INVOKESPECIAL Packet.<init> (LPacket;II)V
    ASTORE 2
   L14
    LINENUMBER 20 L14
    ALOAD 1
    ICONST_3
    SIPUSH 3000
    ALOAD 2
    INVOKEVIRTUAL Scheduler.addHandlerTask (IILPacket;)V
   L15
    LINENUMBER 22 L15
    ALOAD 1
    ICONST_4
    SIPUSH 4000
    ACONST_NULL
    POP
    ACONST_NULL
    INVOKEVIRTUAL Scheduler.addDeviceTask (IILPacket;)V
   L16
    LINENUMBER 24 L16
    ALOAD 1
    ICONST_5
    SIPUSH 5000
    ACONST_NULL
    POP
    ACONST_NULL
    INVOKEVIRTUAL Scheduler.addDeviceTask (IILPacket;)V
   L17
    LINENUMBER 26 L17
    ALOAD 1
    INVOKEVIRTUAL Scheduler.schedule ()V
   L18
    RETURN
   L19
    LOCALVARIABLE scheduler LScheduler; L1 L18 1
    LOCALVARIABLE queue LPacket; L4 L18 2
    LOCALVARIABLE this LRichards; L0 L19 0
    MAXSTACK = 5
    MAXLOCALS = 3

  // access flags 0x1
  public <init>()V
   L0
    LINENUMBER 43 L0
    ALOAD 0
    INVOKESPECIAL java/lang/Object.<init> ()V
   L1
    LINENUMBER 1 L1
    RETURN
   L2
    LOCALVARIABLE this LRichards; L0 L2 0
    MAXSTACK = 1
    MAXLOCALS = 1
}
