// class version 50.0 (50)
// access flags 0x21
public class Scheduler {

  // compiled from: Test.scala

  @Lscala/reflect/ScalaSignature;(bytes="\u0006\u0001\u0005}a\u0001B\u0001\u0003\u0001\u0015\u0011\u0011bU2iK\u0012,H.\u001a:\u000b\u0003\r\u0009q\u0001P3naRLhh\u0001\u0001\u0014\u0005\u00011\u0001CA\u0004\u000b\u001b\u0005A!\"A\u0005\u0002\u000bM\u001c\u0017\r\\1\n\u0005-A!AB!osJ+g\rC\u0003\u000e\u0001\u0011\u0005a\"\u0001\u0004=S:LGO\u0010\u000b\u0002\u001fA\u0011\u0001\u0003A\u0007\u0002\u0005!9!\u0003\u0001a\u0001\n\u0003\u0019\u0012AC9vKV,7i\\;oiV\u0009A\u0003\u0005\u0002\u0008+%\u0011a\u0003\u0003\u0002\u0004\u0013:$\u0008b\u0002\r\u0001\u0001\u0004%\u0009!G\u0001\u000fcV,W/Z\"pk:$x\u000cJ3r)\u0009QR\u0004\u0005\u0002\u00087%\u0011A\u0004\u0003\u0002\u0005+:LG\u000fC\u0004\u001f/\u0005\u0005\u0009\u0019\u0001\u000b\u0002\u0007a$\u0013\u0007\u0003\u0004!\u0001\u0001\u0006K\u0001F\u0001\u000ccV,W/Z\"pk:$\u0008\u0005C\u0004#\u0001\u0001\u0007I\u0011A\n\u0002\u0013!|G\u000eZ\"pk:$\u0008b\u0002\u0013\u0001\u0001\u0004%\u0009!J\u0001\u000eQ>dGmQ8v]R|F%Z9\u0015\u0005i1\u0003b\u0002\u0010$\u0003\u0003\u0005\r\u0001\u0006\u0005\u0007Q\u0001\u0001\u000b\u0015\u0002\u000b\u0002\u0015!|G\u000eZ\"pk:$\u0008\u0005C\u0004+\u0001\u0001\u0007I\u0011A\u0016\u0002\u0015\r,(O]3oiR\u001b'-F\u0001-!\u0009\u0001R&\u0003\u0002/\u0005\u0009\u0001B+Y:l\u0007>tGO]8m\u00052|7m\u001b\u0005\u0008a\u0001\u0001\r\u0011\"\u00012\u00039\u0019WO\u001d:f]R$6MY0%KF$\"A\u0007\u001a\u0009\u000fyy\u0013\u0011!a\u0001Y!1A\u0007\u0001Q!\n1\n1bY;se\u0016tG\u000fV2cA!9a\u0007\u0001a\u0001\n\u0003\u0019\u0012!C2veJ,g\u000e^%e\u0011\u001dA\u0004\u00011A\u0005\u0002e\nQbY;se\u0016tG/\u00133`I\u0015\u000cHC\u0001\u000e;\u0011\u001dqr'!AA\u0002QAa\u0001\u0010\u0001!B\u0013!\u0012AC2veJ,g\u000e^%eA!9a\u0008\u0001a\u0001\n\u0003Y\u0013\u0001\u00027jgRDq\u0001\u0011\u0001A\u0002\u0013\u0005\u0011)\u0001\u0005mSN$x\u000cJ3r)\u0009Q\"\u0009C\u0004\u001f\u0005\u0005\u0009\u0019\u0001\u0017\u0009\r\u0011\u0003\u0001\u0015)\u0003-\u0003\u0015a\u0017n\u001d;!\u0011\u001d1\u0005A1A\u0005\u0002\u001d\u000baA\u00197pG.\u001cX#\u0001%\u0011\u0007\u001dIE&\u0003\u0002K\u0011\u0009)\u0011I\u001d:bs\"1A\n\u0001Q\u0001\n!\u000bqA\u00197pG.\u001c\u0008\u0005C\u0003O\u0001\u0011\u0005q*A\u0006bI\u0012LE\r\\3UCN\\G#\u0002\u000eQ%RK\u0006\"B)N\u0001\u0004!\u0012AA5e\u0011\u0015\u0019V\n1\u0001\u0015\u0003!\u0001(/[8sSRL\u0008\"B+N\u0001\u00041\u0016!B9vKV,\u0007C\u0001\u0009X\u0013\u0009A&A\u0001\u0004QC\u000e\\W\r\u001e\u0005\u000656\u0003\r\u0001F\u0001\u0006G>,h\u000e\u001e\u0005\u00069\u0002!\u0009!X\u0001\u000eC\u0012$wk\u001c:lKJ$\u0016m]6\u0015\u0009iqv\u000c\u0019\u0005\u0006#n\u0003\r\u0001\u0006\u0005\u0006'n\u0003\r\u0001\u0006\u0005\u0006+n\u0003\rA\u0016\u0005\u0006E\u0002!\u0009aY\u0001\u000fC\u0012$\u0007*\u00198eY\u0016\u0014H+Y:l)\u0011QB-\u001a4\u0009\u000bE\u000b\u0007\u0019\u0001\u000b\u0009\u000bM\u000b\u0007\u0019\u0001\u000b\u0009\u000bU\u000b\u0007\u0019\u0001,\u0009\u000b!\u0004A\u0011A5\u0002\u001b\u0005$G\rR3wS\u000e,G+Y:l)\u0011Q\"n\u001b7\u0009\u000bE;\u0007\u0019\u0001\u000b\u0009\u000bM;\u0007\u0019\u0001\u000b\u0009\u000bU;\u0007\u0019\u0001,\u0009\u000b9\u0004A\u0011A8\u0002\u001d\u0005$GMU;o]&tw\rV1tWR)!\u0004]9sg\")\u0011+\u001ca\u0001)!)1+\u001ca\u0001)!)Q+\u001ca\u0001-\")A/\u001ca\u0001k\u0006!A/Y:l!\u0009\u0001b/\u0003\u0002x\u0005\u0009!A+Y:l\u0011\u0015I\u0008\u0001\"\u0001{\u0003\u001d\u0009G\r\u001a+bg.$RAG>}{zDQ!\u0015=A\u0002QAQa\u0015=A\u0002QAQ!\u0016=A\u0002YCQ\u0001\u001e=A\u0002UDq!!\u0001\u0001\u0009\u0003\u0009\u0019!\u0001\u0005tG\",G-\u001e7f)\u0005Q\u0002bBA\u0004\u0001\u0011\u0005\u0011\u0011B\u0001\u0008e\u0016dW-Y:f)\ra\u00131\u0002\u0005\u0007#\u0006\u0015\u0001\u0019\u0001\u000b\u0009\u000f\u0005=\u0001\u0001\"\u0001\u0002\u0012\u0005Y\u0001n\u001c7e\u0007V\u0014(/\u001a8u)\u0005a\u0003bBA\u000b\u0001\u0011\u0005\u0011\u0011C\u0001\u000fgV\u001c\u0008/\u001a8e\u0007V\u0014(/\u001a8u\u0011\u0019)\u0006\u0001\"\u0001\u0002\u001aQ\u0019A&a\u0007\u0009\u000f\u0005u\u0011q\u0003a\u0001-\u00061\u0001/Y2lKR\u0004")

  ATTRIBUTE ScalaSig : unknown

  ATTRIBUTE ScalaInlineInfo : unknown

  // access flags 0x2
  private I queueCount

  // access flags 0x2
  private I holdCount

  // access flags 0x2
  private LTaskControlBlock; currentTcb

  // access flags 0x2
  private I currentId

  // access flags 0x2
  private LTaskControlBlock; list

  // access flags 0x12
  private final [LTaskControlBlock; blocks

  // access flags 0x1
  public queueCount()I
   L0
    LINENUMBER 76 L0
    ALOAD 0
    GETFIELD Scheduler.queueCount : I
    IRETURN
   L1
    LOCALVARIABLE this LScheduler; L0 L1 0
    MAXSTACK = 1
    MAXLOCALS = 1

  // access flags 0x1
  public queueCount_$eq(I)V
   L0
    LINENUMBER 76 L0
    ALOAD 0
    ILOAD 1
    PUTFIELD Scheduler.queueCount : I
    RETURN
   L1
    LOCALVARIABLE this LScheduler; L0 L1 0
    LOCALVARIABLE x$1 I L0 L1 1
    MAXSTACK = 2
    MAXLOCALS = 2

  // access flags 0x1
  public holdCount()I
   L0
    LINENUMBER 77 L0
    ALOAD 0
    GETFIELD Scheduler.holdCount : I
    IRETURN
   L1
    LOCALVARIABLE this LScheduler; L0 L1 0
    MAXSTACK = 1
    MAXLOCALS = 1

  // access flags 0x1
  public holdCount_$eq(I)V
   L0
    LINENUMBER 77 L0
    ALOAD 0
    ILOAD 1
    PUTFIELD Scheduler.holdCount : I
    RETURN
   L1
    LOCALVARIABLE this LScheduler; L0 L1 0
    LOCALVARIABLE x$1 I L0 L1 1
    MAXSTACK = 2
    MAXLOCALS = 2

  // access flags 0x1
  public currentTcb()LTaskControlBlock;
   L0
    LINENUMBER 78 L0
    ALOAD 0
    GETFIELD Scheduler.currentTcb : LTaskControlBlock;
    ARETURN
   L1
    LOCALVARIABLE this LScheduler; L0 L1 0
    MAXSTACK = 1
    MAXLOCALS = 1

  // access flags 0x1
  public currentTcb_$eq(LTaskControlBlock;)V
   L0
    LINENUMBER 78 L0
    ALOAD 0
    ALOAD 1
    PUTFIELD Scheduler.currentTcb : LTaskControlBlock;
    RETURN
   L1
    LOCALVARIABLE this LScheduler; L0 L1 0
    LOCALVARIABLE x$1 LTaskControlBlock; L0 L1 1
    MAXSTACK = 2
    MAXLOCALS = 2

  // access flags 0x1
  public currentId()I
   L0
    LINENUMBER 79 L0
    ALOAD 0
    GETFIELD Scheduler.currentId : I
    IRETURN
   L1
    LOCALVARIABLE this LScheduler; L0 L1 0
    MAXSTACK = 1
    MAXLOCALS = 1

  // access flags 0x1
  public currentId_$eq(I)V
   L0
    LINENUMBER 79 L0
    ALOAD 0
    ILOAD 1
    PUTFIELD Scheduler.currentId : I
    RETURN
   L1
    LOCALVARIABLE this LScheduler; L0 L1 0
    LOCALVARIABLE x$1 I L0 L1 1
    MAXSTACK = 2
    MAXLOCALS = 2

  // access flags 0x1
  public list()LTaskControlBlock;
   L0
    LINENUMBER 80 L0
    ALOAD 0
    GETFIELD Scheduler.list : LTaskControlBlock;
    ARETURN
   L1
    LOCALVARIABLE this LScheduler; L0 L1 0
    MAXSTACK = 1
    MAXLOCALS = 1

  // access flags 0x1
  public list_$eq(LTaskControlBlock;)V
   L0
    LINENUMBER 80 L0
    ALOAD 0
    ALOAD 1
    PUTFIELD Scheduler.list : LTaskControlBlock;
    RETURN
   L1
    LOCALVARIABLE this LScheduler; L0 L1 0
    LOCALVARIABLE x$1 LTaskControlBlock; L0 L1 1
    MAXSTACK = 2
    MAXLOCALS = 2

  // access flags 0x1
  public blocks()[LTaskControlBlock;
   L0
    LINENUMBER 81 L0
    ALOAD 0
    GETFIELD Scheduler.blocks : [LTaskControlBlock;
    ARETURN
   L1
    LOCALVARIABLE this LScheduler; L0 L1 0
    MAXSTACK = 1
    MAXLOCALS = 1

  // access flags 0x1
  public addIdleTask(IILPacket;I)V
   L0
    LINENUMBER 85 L0
    ALOAD 0
    ILOAD 1
    ILOAD 2
    ALOAD 3
    NEW IdleTask
    DUP
    ALOAD 0
    ICONST_1
    ILOAD 4
    INVOKESPECIAL IdleTask.<init> (LScheduler;II)V
    INVOKEVIRTUAL Scheduler.addRunningTask (IILPacket;LTask;)V
    RETURN
   L1
    LOCALVARIABLE this LScheduler; L0 L1 0
    LOCALVARIABLE id I L0 L1 1
    LOCALVARIABLE priority I L0 L1 2
    LOCALVARIABLE queue LPacket; L0 L1 3
    LOCALVARIABLE count I L0 L1 4
    MAXSTACK = 9
    MAXLOCALS = 5

  // access flags 0x1
  public addWorkerTask(IILPacket;)V
   L0
    LINENUMBER 90 L0
    ALOAD 0
    ILOAD 1
    ILOAD 2
    ALOAD 3
    NEW WorkerTask
    DUP
    ALOAD 0
    ICONST_2
    ICONST_0
    INVOKESPECIAL WorkerTask.<init> (LScheduler;II)V
    INVOKEVIRTUAL Scheduler.addTask (IILPacket;LTask;)V
    RETURN
   L1
    LOCALVARIABLE this LScheduler; L0 L1 0
    LOCALVARIABLE id I L0 L1 1
    LOCALVARIABLE priority I L0 L1 2
    LOCALVARIABLE queue LPacket; L0 L1 3
    MAXSTACK = 9
    MAXLOCALS = 4

  // access flags 0x1
  public addHandlerTask(IILPacket;)V
   L0
    LINENUMBER 95 L0
    ALOAD 0
    ILOAD 1
    ILOAD 2
    ALOAD 3
    NEW HandlerTask
    DUP
    ALOAD 0
    INVOKESPECIAL HandlerTask.<init> (LScheduler;)V
    INVOKEVIRTUAL Scheduler.addTask (IILPacket;LTask;)V
    RETURN
   L1
    LOCALVARIABLE this LScheduler; L0 L1 0
    LOCALVARIABLE id I L0 L1 1
    LOCALVARIABLE priority I L0 L1 2
    LOCALVARIABLE queue LPacket; L0 L1 3
    MAXSTACK = 7
    MAXLOCALS = 4

  // access flags 0x1
  public addDeviceTask(IILPacket;)V
   L0
    LINENUMBER 100 L0
    ALOAD 0
    ILOAD 1
    ILOAD 2
    ALOAD 3
    NEW DeviceTask
    DUP
    ALOAD 0
    INVOKESPECIAL DeviceTask.<init> (LScheduler;)V
    INVOKEVIRTUAL Scheduler.addTask (IILPacket;LTask;)V
    RETURN
   L1
    LOCALVARIABLE this LScheduler; L0 L1 0
    LOCALVARIABLE id I L0 L1 1
    LOCALVARIABLE priority I L0 L1 2
    LOCALVARIABLE queue LPacket; L0 L1 3
    MAXSTACK = 7
    MAXLOCALS = 4

  // access flags 0x1
  public addRunningTask(IILPacket;LTask;)V
   L0
    LINENUMBER 105 L0
    ALOAD 0
    ILOAD 1
    ILOAD 2
    ALOAD 3
    ALOAD 4
    INVOKEVIRTUAL Scheduler.addTask (IILPacket;LTask;)V
   L1
    LINENUMBER 106 L1
    ALOAD 0
    INVOKEVIRTUAL Scheduler.currentTcb ()LTaskControlBlock;
    INVOKEVIRTUAL TaskControlBlock.setRunning ()V
    RETURN
   L2
    LOCALVARIABLE this LScheduler; L0 L2 0
    LOCALVARIABLE id I L0 L2 1
    LOCALVARIABLE priority I L0 L2 2
    LOCALVARIABLE queue LPacket; L0 L2 3
    LOCALVARIABLE task LTask; L0 L2 4
    MAXSTACK = 5
    MAXLOCALS = 5

  // access flags 0x1
  public addTask(IILPacket;LTask;)V
   L0
    LINENUMBER 111 L0
    ALOAD 0
    NEW TaskControlBlock
    DUP
    ALOAD 0
    INVOKEVIRTUAL Scheduler.list ()LTaskControlBlock;
    ILOAD 1
    ILOAD 2
    ALOAD 3
    ALOAD 4
    INVOKESPECIAL TaskControlBlock.<init> (LTaskControlBlock;IILPacket;LTask;)V
    INVOKEVIRTUAL Scheduler.currentTcb_$eq (LTaskControlBlock;)V
   L1
    LINENUMBER 112 L1
    ALOAD 0
    ALOAD 0
    INVOKEVIRTUAL Scheduler.currentTcb ()LTaskControlBlock;
    INVOKEVIRTUAL Scheduler.list_$eq (LTaskControlBlock;)V
   L2
    LINENUMBER 113 L2
    ALOAD 0
    INVOKEVIRTUAL Scheduler.blocks ()[LTaskControlBlock;
    ILOAD 1
    ALOAD 0
    INVOKEVIRTUAL Scheduler.currentTcb ()LTaskControlBlock;
    AASTORE
    RETURN
   L3
    LOCALVARIABLE this LScheduler; L0 L3 0
    LOCALVARIABLE id I L0 L3 1
    LOCALVARIABLE priority I L0 L3 2
    LOCALVARIABLE queue LPacket; L0 L3 3
    LOCALVARIABLE task LTask; L0 L3 4
    MAXSTACK = 8
    MAXLOCALS = 5

  // access flags 0x1
  public schedule()V
   L0
    LINENUMBER 118 L0
    ALOAD 0
    ALOAD 0
    INVOKEVIRTUAL Scheduler.list ()LTaskControlBlock;
    INVOKEVIRTUAL Scheduler.currentTcb_$eq (LTaskControlBlock;)V
   L1
    LINENUMBER 119 L1
   FRAME SAME
    ALOAD 0
    INVOKEVIRTUAL Scheduler.currentTcb ()LTaskControlBlock;
    IFNULL L2
    GOTO L3
   L3
    LINENUMBER 120 L3
   FRAME SAME
    ALOAD 0
    INVOKEVIRTUAL Scheduler.currentTcb ()LTaskControlBlock;
    INVOKEVIRTUAL TaskControlBlock.isHeldOrSuspended ()Z
    IFNE L4
    GOTO L5
   L4
    LINENUMBER 121 L4
   FRAME SAME
    ALOAD 0
    ALOAD 0
    INVOKEVIRTUAL Scheduler.currentTcb ()LTaskControlBlock;
    INVOKEVIRTUAL TaskControlBlock.link ()LTaskControlBlock;
    INVOKEVIRTUAL Scheduler.currentTcb_$eq (LTaskControlBlock;)V
    GOTO L6
   L5
    LINENUMBER 123 L5
   FRAME SAME
    ALOAD 0
    ALOAD 0
    INVOKEVIRTUAL Scheduler.currentTcb ()LTaskControlBlock;
    INVOKEVIRTUAL TaskControlBlock.id ()I
    INVOKEVIRTUAL Scheduler.currentId_$eq (I)V
   L7
    LINENUMBER 124 L7
    ALOAD 0
    ALOAD 0
    INVOKEVIRTUAL Scheduler.currentTcb ()LTaskControlBlock;
    INVOKEVIRTUAL TaskControlBlock.run ()LTaskControlBlock;
    INVOKEVIRTUAL Scheduler.currentTcb_$eq (LTaskControlBlock;)V
   L6
    LINENUMBER 120 L6
   FRAME SAME
    GOTO L1
   L2
    LINENUMBER 119 L2
   FRAME SAME
    RETURN
   L8
    LOCALVARIABLE this LScheduler; L0 L8 0
    MAXSTACK = 2
    MAXLOCALS = 1

  // access flags 0x1
  public release(I)LTaskControlBlock;
   L0
    LINENUMBER 131 L0
    ALOAD 0
    INVOKEVIRTUAL Scheduler.blocks ()[LTaskControlBlock;
    ILOAD 1
    AALOAD
   L1
    ASTORE 2
   L2
    LINENUMBER 132 L2
    ALOAD 2
    IFNULL L3
    GOTO L4
   L3
   FRAME APPEND [TaskControlBlock]
    ALOAD 2
    GOTO L5
   L4
    LINENUMBER 134 L4
   FRAME SAME
    ALOAD 2
    INVOKEVIRTUAL TaskControlBlock.markAsNotHeld ()V
   L6
    LINENUMBER 135 L6
    ALOAD 2
    INVOKEVIRTUAL TaskControlBlock.priority ()I
    ALOAD 0
    INVOKEVIRTUAL Scheduler.currentTcb ()LTaskControlBlock;
    INVOKEVIRTUAL TaskControlBlock.priority ()I
    IF_ICMPGT L7
    GOTO L8
   L7
   FRAME SAME
    ALOAD 2
    GOTO L5
   L8
    LINENUMBER 136 L8
   FRAME SAME
    ALOAD 0
    INVOKEVIRTUAL Scheduler.currentTcb ()LTaskControlBlock;
   L5
   FRAME SAME1 TaskControlBlock
    ARETURN
   L9
    LOCALVARIABLE tcb LTaskControlBlock; L1 L5 2
    LOCALVARIABLE this LScheduler; L0 L9 0
    LOCALVARIABLE id I L0 L9 1
    MAXSTACK = 2
    MAXLOCALS = 3

  // access flags 0x1
  public holdCurrent()LTaskControlBlock;
   L0
    LINENUMBER 146 L0
    ALOAD 0
    ALOAD 0
    INVOKEVIRTUAL Scheduler.holdCount ()I
    ICONST_1
    IADD
    INVOKEVIRTUAL Scheduler.holdCount_$eq (I)V
   L1
    LINENUMBER 147 L1
    ALOAD 0
    INVOKEVIRTUAL Scheduler.currentTcb ()LTaskControlBlock;
    INVOKEVIRTUAL TaskControlBlock.markAsHeld ()V
   L2
    LINENUMBER 148 L2
    ALOAD 0
    INVOKEVIRTUAL Scheduler.currentTcb ()LTaskControlBlock;
    INVOKEVIRTUAL TaskControlBlock.link ()LTaskControlBlock;
    ARETURN
   L3
    LOCALVARIABLE this LScheduler; L0 L3 0
    MAXSTACK = 3
    MAXLOCALS = 1

  // access flags 0x1
  public suspendCurrent()LTaskControlBlock;
   L0
    LINENUMBER 157 L0
    ALOAD 0
    INVOKEVIRTUAL Scheduler.currentTcb ()LTaskControlBlock;
    INVOKEVIRTUAL TaskControlBlock.markAsSuspended ()V
   L1
    LINENUMBER 158 L1
    ALOAD 0
    INVOKEVIRTUAL Scheduler.currentTcb ()LTaskControlBlock;
    ARETURN
   L2
    LOCALVARIABLE this LScheduler; L0 L2 0
    MAXSTACK = 1
    MAXLOCALS = 1

  // access flags 0x1
  public queue(LPacket;)LTaskControlBlock;
   L0
    LINENUMBER 167 L0
    ALOAD 0
    INVOKEVIRTUAL Scheduler.blocks ()[LTaskControlBlock;
    ALOAD 1
    INVOKEVIRTUAL Packet.id ()I
    AALOAD
   L1
    ASTORE 2
   L2
    LINENUMBER 168 L2
    ALOAD 2
    IFNULL L3
    GOTO L4
   L3
   FRAME APPEND [TaskControlBlock]
    ALOAD 2
    GOTO L5
   L4
    LINENUMBER 170 L4
   FRAME SAME
    ALOAD 0
    ALOAD 0
    INVOKEVIRTUAL Scheduler.queueCount ()I
    ICONST_1
    IADD
    INVOKEVIRTUAL Scheduler.queueCount_$eq (I)V
   L6
    LINENUMBER 171 L6
    ALOAD 1
    ACONST_NULL
    POP
    ACONST_NULL
    INVOKEVIRTUAL Packet.link_$eq (LPacket;)V
   L7
    LINENUMBER 172 L7
    ALOAD 1
    ALOAD 0
    INVOKEVIRTUAL Scheduler.currentId ()I
    INVOKEVIRTUAL Packet.id_$eq (I)V
   L8
    LINENUMBER 173 L8
    ALOAD 2
    ALOAD 0
    INVOKEVIRTUAL Scheduler.currentTcb ()LTaskControlBlock;
    ALOAD 1
    INVOKEVIRTUAL TaskControlBlock.checkPriorityAdd (LTaskControlBlock;LPacket;)LTaskControlBlock;
   L5
   FRAME SAME1 TaskControlBlock
    ARETURN
   L9
    LOCALVARIABLE t LTaskControlBlock; L1 L5 2
    LOCALVARIABLE this LScheduler; L0 L9 0
    LOCALVARIABLE packet LPacket; L0 L9 1
    MAXSTACK = 3
    MAXLOCALS = 3

  // access flags 0x1
  public <init>()V
   L0
    LINENUMBER 178 L0
    ALOAD 0
    INVOKESPECIAL java/lang/Object.<init> ()V
   L1
    LINENUMBER 76 L1
    ALOAD 0
    ICONST_0
    PUTFIELD Scheduler.queueCount : I
   L2
    LINENUMBER 77 L2
    ALOAD 0
    ICONST_0
    PUTFIELD Scheduler.holdCount : I
   L3
    LINENUMBER 78 L3
    ALOAD 0
    ACONST_NULL
    POP
    ACONST_NULL
    PUTFIELD Scheduler.currentTcb : LTaskControlBlock;
   L4
    LINENUMBER 79 L4
    ALOAD 0
    ICONST_0
    PUTFIELD Scheduler.currentId : I
   L5
    LINENUMBER 80 L5
    ALOAD 0
    ACONST_NULL
    POP
    ACONST_NULL
    PUTFIELD Scheduler.list : LTaskControlBlock;
   L6
    LINENUMBER 81 L6
    ALOAD 0
    BIPUSH 6
    ANEWARRAY TaskControlBlock
    PUTFIELD Scheduler.blocks : [LTaskControlBlock;
   L7
    LINENUMBER 74 L7
    RETURN
   L8
    LOCALVARIABLE this LScheduler; L0 L8 0
    MAXSTACK = 2
    MAXLOCALS = 1
}
