// class version 50.0 (50)
// access flags 0x21
public class TaskControlBlock {

  // compiled from: Test.scala

  @Lscala/reflect/ScalaSignature;(bytes="\u0006\u0001!4A!\u0001\u0002\u0001\u000b\u0009\u0001B+Y:l\u0007>tGO]8m\u00052|7m\u001b\u0006\u0002\u0007\u00059A(Z7qift4\u0001A\n\u0003\u0001\u0019\u0001\"a\u0002\u0006\u000e\u0003!Q\u0011!C\u0001\u0006g\u000e\u000cG.Y\u0005\u0003\u0017!\u0011a!\u00118z%\u00164\u0007\u0002C\u0007\u0001\u0005\u000b\u0007I\u0011\u0001\u0008\u0002\u00091Lgn[\u000b\u0002\u001fA\u0011\u0001\u0003A\u0007\u0002\u0005!A!\u0003\u0001B\u0001B\u0003%q\"A\u0003mS:\\\u0007\u0005\u0003\u0005\u0015\u0001\u0009\u0015\r\u0011\"\u0001\u0016\u0003\u0009IG-F\u0001\u0017!\u00099q#\u0003\u0002\u0019\u0011\u0009\u0019\u0011J\u001c;\u0009\u0011i\u0001!\u0011!Q\u0001\nY\u00091!\u001b3!\u0011!a\u0002A!b\u0001\n\u0003)\u0012\u0001\u00039sS>\u0014\u0018\u000e^=\u0009\u0011y\u0001!\u0011!Q\u0001\nY\u0009\u0011\u0002\u001d:j_JLG/\u001f\u0011\u0009\u0011\u0001\u0002!\u00111A\u0005\u0002\u0005\nQ!];fk\u0016,\u0012A\u0009\u0009\u0003!\rJ!\u0001\n\u0002\u0003\rA\u000b7m[3u\u0011!1\u0003A!a\u0001\n\u00039\u0013!C9vKV,w\u000cJ3r)\u0009A3\u0006\u0005\u0002\u0008S%\u0011!\u0006\u0003\u0002\u0005+:LG\u000fC\u0004-K\u0005\u0005\u0009\u0019\u0001\u0012\u0002\u0007a$\u0013\u0007\u0003\u0005/\u0001\u0009\u0005\u0009\u0015)\u0003#\u0003\u0019\u0009X/Z;fA!A\u0001\u0007\u0001B\u0001B\u0003%\u0011'\u0001\u0003uCN\\\u0007C\u0001\u00093\u0013\u0009\u0019$A\u0001\u0003UCN\\\u0007\"B\u001b\u0001\u0009\u00031\u0014A\u0002\u001fj]&$h\u0008\u0006\u0004\u0010oaJ$h\u000f\u0005\u0006\u001bQ\u0002\ra\u0004\u0005\u0006)Q\u0002\rA\u0006\u0005\u00069Q\u0002\rA\u0006\u0005\u0006AQ\u0002\rA\u0009\u0005\u0006aQ\u0002\r!\r\u0005\u0008{\u0001\u0001\r\u0011\"\u0001\u0016\u0003\u0015\u0019H/\u0019;f\u0011\u001dy\u0004\u00011A\u0005\u0002\u0001\u000b\u0011b\u001d;bi\u0016|F%Z9\u0015\u0005!\n\u0005b\u0002\u0017?\u0003\u0003\u0005\rA\u0006\u0005\u0007\u0007\u0002\u0001\u000b\u0015\u0002\u000c\u0002\rM$\u0018\r^3!\u0011\u0015)\u0005\u0001\"\u0001G\u0003)\u0019X\r\u001e*v]:Lgn\u001a\u000b\u0002Q!)\u0001\n\u0001C\u0001\r\u0006iQ.\u0019:l\u0003Ntu\u000e\u001e%fY\u0012DQA\u0013\u0001\u0005\u0002\u0019\u000b!\"\\1sW\u0006\u001b\u0008*\u001a7e\u0011\u0015a\u0005\u0001\"\u0001N\u0003EI7\u000fS3mI>\u00138+^:qK:$W\r\u001a\u000b\u0002\u001dB\u0011qaT\u0005\u0003!\"\u0011qAQ8pY\u0016\u000cg\u000eC\u0003S\u0001\u0011\u0005a)A\u0008nCJ\\\u0017i]*vgB,g\u000eZ3e\u0011\u0015!\u0006\u0001\"\u0001G\u00039i\u0017M]6BgJ+hN\\1cY\u0016DQA\u0016\u0001\u0005\u0002]\u000b1A];o)\u0005y\u0001\"B-\u0001\u0009\u0003Q\u0016\u0001E2iK\u000e\\\u0007K]5pe&$\u00180\u00113e)\ry1\u000c\u0018\u0005\u0006aa\u0003\ra\u0004\u0005\u0006;b\u0003\rAI\u0001\u0007a\u0006\u001c7.\u001a;\u0009\u000b}\u0003A\u0011\u00091\u0002\u0011Q|7\u000b\u001e:j]\u001e$\u0012!\u0019\u0009\u0003E\u0016t!aB2\n\u0005\u0011D\u0011A\u0002)sK\u0012,g-\u0003\u0002gO\n11\u000b\u001e:j]\u001eT!\u0001\u001a\u0005")

  ATTRIBUTE ScalaSig : unknown

  ATTRIBUTE ScalaInlineInfo : unknown

  // access flags 0x12
  private final LTaskControlBlock; link

  // access flags 0x12
  private final I id

  // access flags 0x12
  private final I priority

  // access flags 0x2
  private LPacket; queue

  // access flags 0x12
  private final LTask; task

  // access flags 0x2
  private I state

  // access flags 0x1
  public link()LTaskControlBlock;
   L0
    LINENUMBER 206 L0
    ALOAD 0
    GETFIELD TaskControlBlock.link : LTaskControlBlock;
    ARETURN
   L1
    LOCALVARIABLE this LTaskControlBlock; L0 L1 0
    MAXSTACK = 1
    MAXLOCALS = 1

  // access flags 0x1
  public id()I
   L0
    LINENUMBER 206 L0
    ALOAD 0
    GETFIELD TaskControlBlock.id : I
    IRETURN
   L1
    LOCALVARIABLE this LTaskControlBlock; L0 L1 0
    MAXSTACK = 1
    MAXLOCALS = 1

  // access flags 0x1
  public priority()I
   L0
    LINENUMBER 206 L0
    ALOAD 0
    GETFIELD TaskControlBlock.priority : I
    IRETURN
   L1
    LOCALVARIABLE this LTaskControlBlock; L0 L1 0
    MAXSTACK = 1
    MAXLOCALS = 1

  // access flags 0x1
  public queue()LPacket;
   L0
    LINENUMBER 206 L0
    ALOAD 0
    GETFIELD TaskControlBlock.queue : LPacket;
    ARETURN
   L1
    LOCALVARIABLE this LTaskControlBlock; L0 L1 0
    MAXSTACK = 1
    MAXLOCALS = 1

  // access flags 0x1
  public queue_$eq(LPacket;)V
   L0
    LINENUMBER 206 L0
    ALOAD 0
    ALOAD 1
    PUTFIELD TaskControlBlock.queue : LPacket;
    RETURN
   L1
    LOCALVARIABLE this LTaskControlBlock; L0 L1 0
    LOCALVARIABLE x$1 LPacket; L0 L1 1
    MAXSTACK = 2
    MAXLOCALS = 2

  // access flags 0x1
  public state()I
   L0
    LINENUMBER 208 L0
    ALOAD 0
    GETFIELD TaskControlBlock.state : I
    IRETURN
   L1
    LOCALVARIABLE this LTaskControlBlock; L0 L1 0
    MAXSTACK = 1
    MAXLOCALS = 1

  // access flags 0x1
  public state_$eq(I)V
   L0
    LINENUMBER 208 L0
    ALOAD 0
    ILOAD 1
    PUTFIELD TaskControlBlock.state : I
    RETURN
   L1
    LOCALVARIABLE this LTaskControlBlock; L0 L1 0
    LOCALVARIABLE x$1 I L0 L1 1
    MAXSTACK = 2
    MAXLOCALS = 2

  // access flags 0x1
  public setRunning()V
   L0
    LINENUMBER 211 L0
    ALOAD 0
    ICONST_0
    INVOKEVIRTUAL TaskControlBlock.state_$eq (I)V
    RETURN
   L1
    LOCALVARIABLE this LTaskControlBlock; L0 L1 0
    MAXSTACK = 2
    MAXLOCALS = 1

  // access flags 0x1
  public markAsNotHeld()V
   L0
    LINENUMBER 215 L0
    ALOAD 0
    ALOAD 0
    INVOKEVIRTUAL TaskControlBlock.state ()I
    GETSTATIC TaskState$.MODULE$ : LTaskState$;
    INVOKEVIRTUAL TaskState$.NOT_HELD ()I
    IAND
    INVOKEVIRTUAL TaskControlBlock.state_$eq (I)V
    RETURN
   L1
    LOCALVARIABLE this LTaskControlBlock; L0 L1 0
    MAXSTACK = 3
    MAXLOCALS = 1

  // access flags 0x1
  public markAsHeld()V
   L0
    LINENUMBER 219 L0
    ALOAD 0
    ALOAD 0
    INVOKEVIRTUAL TaskControlBlock.state ()I
    ICONST_4
    IOR
    INVOKEVIRTUAL TaskControlBlock.state_$eq (I)V
    RETURN
   L1
    LOCALVARIABLE this LTaskControlBlock; L0 L1 0
    MAXSTACK = 3
    MAXLOCALS = 1

  // access flags 0x1
  public isHeldOrSuspended()Z
   L0
    LINENUMBER 223 L0
    ALOAD 0
    INVOKEVIRTUAL TaskControlBlock.state ()I
    ICONST_4
    IAND
    ICONST_0
    IF_ICMPNE L1
    GOTO L2
   L2
    LINENUMBER 224 L2
   FRAME SAME
    ALOAD 0
    INVOKEVIRTUAL TaskControlBlock.state ()I
    ICONST_2
    IF_ICMPEQ L1
    GOTO L3
   L1
   FRAME SAME
    ICONST_1
    GOTO L4
   L3
   FRAME SAME
    ICONST_0
   L4
   FRAME SAME1 I
    IRETURN
   L5
    LOCALVARIABLE this LTaskControlBlock; L0 L5 0
    MAXSTACK = 2
    MAXLOCALS = 1

  // access flags 0x1
  public markAsSuspended()V
   L0
    LINENUMBER 228 L0
    ALOAD 0
    ALOAD 0
    INVOKEVIRTUAL TaskControlBlock.state ()I
    ICONST_2
    IOR
    INVOKEVIRTUAL TaskControlBlock.state_$eq (I)V
    RETURN
   L1
    LOCALVARIABLE this LTaskControlBlock; L0 L1 0
    MAXSTACK = 3
    MAXLOCALS = 1

  // access flags 0x1
  public markAsRunnable()V
   L0
    LINENUMBER 232 L0
    ALOAD 0
    ALOAD 0
    INVOKEVIRTUAL TaskControlBlock.state ()I
    ICONST_1
    IOR
    INVOKEVIRTUAL TaskControlBlock.state_$eq (I)V
    RETURN
   L1
    LOCALVARIABLE this LTaskControlBlock; L0 L1 0
    MAXSTACK = 3
    MAXLOCALS = 1

  // access flags 0x1
  public run()LTaskControlBlock;
   L0
    LINENUMBER 237 L0
    ALOAD 0
    INVOKEVIRTUAL TaskControlBlock.state ()I
    ICONST_3
    IF_ICMPEQ L1
    GOTO L2
   L1
   FRAME SAME
    ALOAD 0
    INVOKEVIRTUAL TaskControlBlock.queue ()LPacket;
    GOTO L3
   L2
   FRAME SAME
    ACONST_NULL
    POP
    ACONST_NULL
   L3
   FRAME SAME1 Packet
    ASTORE 1
   L4
    LINENUMBER 238 L4
    ALOAD 1
    IFNULL L5
    GOTO L6
   L6
    LINENUMBER 239 L6
   FRAME APPEND [Packet]
    ALOAD 0
    ALOAD 1
    INVOKEVIRTUAL Packet.link ()LPacket;
    INVOKEVIRTUAL TaskControlBlock.queue_$eq (LPacket;)V
   L7
    LINENUMBER 240 L7
    ALOAD 0
    ALOAD 0
    INVOKEVIRTUAL TaskControlBlock.queue ()LPacket;
    IFNULL L8
    GOTO L9
   L8
   FRAME SAME1 TaskControlBlock
    ICONST_0
    GOTO L10
   L9
   FRAME SAME1 TaskControlBlock
    ICONST_1
   L10
   FRAME FULL [TaskControlBlock Packet] [TaskControlBlock I]
    INVOKEVIRTUAL TaskControlBlock.state_$eq (I)V
    GOTO L5
   L5
    LINENUMBER 242 L5
   FRAME SAME
    ALOAD 0
    GETFIELD TaskControlBlock.task : LTask;
    ALOAD 1
    INVOKEVIRTUAL Task.run (LPacket;)LTaskControlBlock;
   L11
    ARETURN
   L12
    LOCALVARIABLE packet LPacket; L3 L11 1
    LOCALVARIABLE this LTaskControlBlock; L0 L12 0
    MAXSTACK = 2
    MAXLOCALS = 2

  // access flags 0x1
  public checkPriorityAdd(LTaskControlBlock;LPacket;)LTaskControlBlock;
   L0
    LINENUMBER 251 L0
    ALOAD 0
    INVOKEVIRTUAL TaskControlBlock.queue ()LPacket;
    IFNULL L1
    GOTO L2
   L1
    LINENUMBER 252 L1
   FRAME SAME
    ALOAD 0
    ALOAD 2
    INVOKEVIRTUAL TaskControlBlock.queue_$eq (LPacket;)V
   L3
    LINENUMBER 253 L3
    ALOAD 0
    INVOKEVIRTUAL TaskControlBlock.markAsRunnable ()V
   L4
    LINENUMBER 254 L4
    ALOAD 0
    INVOKEVIRTUAL TaskControlBlock.priority ()I
    ALOAD 1
    INVOKEVIRTUAL TaskControlBlock.priority ()I
    IF_ICMPGT L5
    GOTO L6
   L5
   FRAME SAME
    ALOAD 0
    GOTO L7
   L6
    LINENUMBER 255 L6
   FRAME SAME
    ALOAD 1
   L7
   FRAME SAME1 TaskControlBlock
    GOTO L8
   L2
    LINENUMBER 257 L2
   FRAME SAME
    ALOAD 0
    ALOAD 2
    ALOAD 0
    INVOKEVIRTUAL TaskControlBlock.queue ()LPacket;
    INVOKEVIRTUAL Packet.addTo (LPacket;)LPacket;
    INVOKEVIRTUAL TaskControlBlock.queue_$eq (LPacket;)V
   L9
    LINENUMBER 258 L9
    ALOAD 1
   L8
   FRAME SAME1 TaskControlBlock
    ARETURN
   L10
    LOCALVARIABLE this LTaskControlBlock; L0 L10 0
    LOCALVARIABLE task LTaskControlBlock; L0 L10 1
    LOCALVARIABLE packet LPacket; L0 L10 2
    MAXSTACK = 3
    MAXLOCALS = 3

  // access flags 0x1
  public toString()Ljava/lang/String;
   L0
    LINENUMBER 262 L0
    NEW scala/StringContext
    DUP
    GETSTATIC scala/Predef$.MODULE$ : Lscala/Predef$;
    ICONST_3
    ANEWARRAY java/lang/String
    DUP
    ICONST_0
    LDC "tcb { "
    AASTORE
    DUP
    ICONST_1
    LDC "@"
    AASTORE
    DUP
    ICONST_2
    LDC " }"
    AASTORE
    CHECKCAST [Ljava/lang/Object;
    INVOKEVIRTUAL scala/Predef$.wrapRefArray ([Ljava/lang/Object;)Lscala/collection/mutable/WrappedArray;
    INVOKESPECIAL scala/StringContext.<init> (Lscala/collection/Seq;)V
    GETSTATIC scala/Predef$.MODULE$ : Lscala/Predef$;
    ICONST_2
    ANEWARRAY java/lang/Object
    DUP
    ICONST_0
    ALOAD 0
    GETFIELD TaskControlBlock.task : LTask;
    AASTORE
    DUP
    ICONST_1
    ALOAD 0
    INVOKEVIRTUAL TaskControlBlock.state ()I
    INVOKESTATIC scala/runtime/BoxesRunTime.boxToInteger (I)Ljava/lang/Integer;
    AASTORE
    INVOKEVIRTUAL scala/Predef$.genericWrapArray (Ljava/lang/Object;)Lscala/collection/mutable/WrappedArray;
    INVOKEVIRTUAL scala/StringContext.s (Lscala/collection/Seq;)Ljava/lang/String;
    ARETURN
   L1
    LOCALVARIABLE this LTaskControlBlock; L0 L1 0
    MAXSTACK = 7
    MAXLOCALS = 1

  // access flags 0x1
  public <init>(LTaskControlBlock;IILPacket;LTask;)V
   L0
    LINENUMBER 206 L0
    ALOAD 0
    ALOAD 1
    PUTFIELD TaskControlBlock.link : LTaskControlBlock;
    ALOAD 0
    ILOAD 2
    PUTFIELD TaskControlBlock.id : I
    ALOAD 0
    ILOAD 3
    PUTFIELD TaskControlBlock.priority : I
    ALOAD 0
    ALOAD 4
    PUTFIELD TaskControlBlock.queue : LPacket;
    ALOAD 0
    ALOAD 5
    PUTFIELD TaskControlBlock.task : LTask;
   L1
    LINENUMBER 270 L1
    ALOAD 0
    INVOKESPECIAL java/lang/Object.<init> ()V
   L2
    LINENUMBER 208 L2
    ALOAD 0
    ALOAD 0
    INVOKEVIRTUAL TaskControlBlock.queue ()LPacket;
    IFNULL L3
    GOTO L4
   L3
   FRAME FULL [TaskControlBlock TaskControlBlock I I Packet Task] [TaskControlBlock]
    ICONST_2
    GOTO L5
   L4
   FRAME SAME1 TaskControlBlock
    ICONST_3
   L5
   FRAME FULL [TaskControlBlock TaskControlBlock I I Packet Task] [TaskControlBlock I]
    PUTFIELD TaskControlBlock.state : I
   L6
    LINENUMBER 206 L6
    RETURN
   L7
    LOCALVARIABLE this LTaskControlBlock; L0 L7 0
    LOCALVARIABLE link LTaskControlBlock; L0 L7 1
    LOCALVARIABLE id I L0 L7 2
    LOCALVARIABLE priority I L0 L7 3
    LOCALVARIABLE queue LPacket; L0 L7 4
    LOCALVARIABLE task LTask; L0 L7 5
    MAXSTACK = 2
    MAXLOCALS = 6
}
